tab_err/__init__.py
tab_err/_error_model.py
tab_err/_utils.py
tab_err/api/__init__.py
tab_err/api/high_level.py
tab_err/api/low_level.py
tab_err/api/mid_level.py
tab_err/error_mechanism/__init__.py
tab_err/error_mechanism/_ear.py
tab_err/error_mechanism/_ecar.py
tab_err/error_mechanism/_enar.py
tab_err/error_mechanism/_error_mechanism.py
tab_err/error_type/__init__.py
tab_err/error_type/_add_delta.py
tab_err/error_type/_category_swap.py
tab_err/error_type/_config.py
tab_err/error_type/_error_type.py
tab_err/error_type/_extraneous.py
tab_err/error_type/_missing.py
tab_err/error_type/_mistype.py
tab_err/error_type/_mojibake.py
tab_err/error_type/_outlier.py
tab_err/error_type/_permutate.py
tab_err/error_type/_replace.py
tab_err/error_type/_typo.py
tab_err/error_type/_wrong_unit.py
tab_err-0.2.1.dist-info/licenses/LICENSE
tab_err-0.2.1.dist-info/METADATA
tab_err-0.2.1.dist-info/WHEEL
tab_err-0.2.1.dist-info/top_level.txt
tab_err-0.2.1.dist-info/RECORD
