Metadata-Version: 2.4
Name: tab_err
Version: 0.2.1
Summary: Fully-controllable error generation for tabular data.
Author-email: Philipp Jung <philippjung@posteo.de>, Sebastian Jäger <tab_err@sebastian-jaeger.me>
License: Apache License 2.0
Project-URL: homepage, https://tab-err.readthedocs.io/latest/
Project-URL: repository, https://github.com/calgo-lab/tab_err
Project-URL: documentation, https://tab-err.readthedocs.io/latest/
Project-URL: Bug Tracker, https://github.com/calgo-lab/tab_err/issues
Keywords: tabular-data,data-quality,error-modeling,data-errors
Classifier: Intended Audience :: Developers
Classifier: Intended Audience :: Science/Research
Classifier: Natural Language :: English
Classifier: License :: OSI Approved :: Apache Software License
Classifier: Programming Language :: Python :: 3.9
Classifier: Programming Language :: Python :: 3.10
Classifier: Programming Language :: Python :: 3.11
Classifier: Programming Language :: Python :: 3.12
Classifier: Operating System :: POSIX :: Linux
Classifier: Operating System :: MacOS
Classifier: Operating System :: Microsoft :: Windows
Requires-Python: <3.13,>=3.9
License-File: LICENSE
Requires-Dist: pandas<2.4.0,>=2.3.0
Dynamic: license-file
